{"question":"Over what period of time does the story take place?","answers":["two days"],"document_id":"21bac5f922f18e036b67f8ac938fccc238adc55c","doc_idx":1158}
{"question":"What is the occupation of the four main characters?","answers":["real estate salesmen","real estate salesman"],"document_id":"21bac5f922f18e036b67f8ac938fccc238adc55c","doc_idx":1158}
{"question":"Blake tells the salesmen that the top two will get the Glengarry leads.  What does he say will happen to the other two salesmen?","answers":["The two salesmen will be fired.","They will be fired"],"document_id":"21bac5f922f18e036b67f8ac938fccc238adc55c","doc_idx":1158}
{"question":"Who admits to breaking into the office?","answers":["Levene"],"document_id":"21bac5f922f18e036b67f8ac938fccc238adc55c","doc_idx":1158}
{"question":"Who does Levene say broke into the office with him?","answers":["Dave Moss.","Moss"],"document_id":"21bac5f922f18e036b67f8ac938fccc238adc55c","doc_idx":1158}
{"question":"Who does Levene try to bribe for some leads?","answers":["Williamson","Office manager John Williamson."],"document_id":"21bac5f922f18e036b67f8ac938fccc238adc55c","doc_idx":1158}
{"question":"What excuse does Lingk use to try and cancel the deal he made on the first day?","answers":["Lingk says his wife has told him to cancel the deal.","His wife told him to cancel the deal"],"document_id":"21bac5f922f18e036b67f8ac938fccc238adc55c","doc_idx":1158}
{"question":"What did the salesmen find when they arrived at the office on the morning of the second day?","answers":["Someone had broken into the office.","The Glengarry leads have been stolen in a burglary."],"document_id":"21bac5f922f18e036b67f8ac938fccc238adc55c","doc_idx":1158}
{"question":"What is wrong with Leven's daughter?","answers":[" with an unknown condition.","She is chronically ill"],"document_id":"21bac5f922f18e036b67f8ac938fccc238adc55c","doc_idx":1158}
{"question":"Why does Williamson say he wants to crush Levene?","answers":["he dislikes him","He doesn't like him."],"document_id":"21bac5f922f18e036b67f8ac938fccc238adc55c","doc_idx":1158}
{"question":"Who is sent to motivate the salesman?","answers":["Blake","Blake."],"document_id":"21bac5f922f18e036b67f8ac938fccc238adc55c","doc_idx":1158}
{"question":"Whose daughter has an unknown medical condition?","answers":["Shelley","Levene"],"document_id":"21bac5f922f18e036b67f8ac938fccc238adc55c","doc_idx":1158}
{"question":"Who does Shelley try to convince to get the Glengarry leads?","answers":["John","John Williamson"],"document_id":"21bac5f922f18e036b67f8ac938fccc238adc55c","doc_idx":1158}
{"question":"What does Williamson want, in order to give away some of the Glengarry leads to Shelley?","answers":["Cash","Cash in advance"," in advance of any sales Shelley makes."],"document_id":"21bac5f922f18e036b67f8ac938fccc238adc55c","doc_idx":1158}
{"question":"Who has told Lingk to cancel the deal? ","answers":["His wife.","His wife"],"document_id":"21bac5f922f18e036b67f8ac938fccc238adc55c","doc_idx":1158}
{"question":"Who tells Lingk that his check has already been deposited?","answers":["Williamson"],"document_id":"21bac5f922f18e036b67f8ac938fccc238adc55c","doc_idx":1158}
{"question":"Who does William tell that he doesn't like him?","answers":["Shelley Levene","Levene"],"document_id":"21bac5f922f18e036b67f8ac938fccc238adc55c","doc_idx":1158}
{"question":"Who talks to Levene about forming a business partnership?","answers":["Roma"],"document_id":"21bac5f922f18e036b67f8ac938fccc238adc55c","doc_idx":1158}
{"question":"Who is in a long running slump?","answers":["Shelley","Shelley Levene."],"document_id":"21bac5f922f18e036b67f8ac938fccc238adc55c","doc_idx":1158}
{"question":"Who worked with Levene to steal the leads?","answers":["Moss","Dave Moss"],"document_id":"21bac5f922f18e036b67f8ac938fccc238adc55c","doc_idx":1158}
{"question":"This story is about how many real estate salesmen?","answers":["Four"],"document_id":"21bac5f922f18e036b67f8ac938fccc238adc55c","doc_idx":1158}
{"question":"Who owns Premier Properties?","answers":["Mitch and Murray."],"document_id":"21bac5f922f18e036b67f8ac938fccc238adc55c","doc_idx":1158}
{"question":"Whose daughter is sick in the hospital?","answers":["Shelley Levene"],"document_id":"21bac5f922f18e036b67f8ac938fccc238adc55c","doc_idx":1158}
{"question":"What is the name of the office manager Shelley Levene tries to charm and bribe?","answers":["John Williamson.","John Williamson"],"document_id":"21bac5f922f18e036b67f8ac938fccc238adc55c","doc_idx":1158}
{"question":"How does Moss suggest they strike back at Mitch and Murray?","answers":["By stealing the Glengarry leads.","By stealing all their leads and sell them to a competing real estate agency."],"document_id":"21bac5f922f18e036b67f8ac938fccc238adc55c","doc_idx":1158}
{"question":"Who does Ricky Roma talk with in the bar?","answers":["James Lingk"],"document_id":"21bac5f922f18e036b67f8ac938fccc238adc55c","doc_idx":1158}
{"question":"Who tells James Lingk to cancel the deal?","answers":["James wife.","His wife"],"document_id":"21bac5f922f18e036b67f8ac938fccc238adc55c","doc_idx":1158}
{"question":"Who breaks into the office?","answers":["Aaronow.","Shelley Levene"],"document_id":"21bac5f922f18e036b67f8ac938fccc238adc55c","doc_idx":1158}
{"question":"Why does John Williamson want to ruin Shelley Levene?","answers":["Because John doesn't like Shelley.","Because he does not like him."],"document_id":"21bac5f922f18e036b67f8ac938fccc238adc55c","doc_idx":1158}
{"question":"Who's office do the police use to interrogate the salesmen?","answers":["Williamson's","John Williamson's"],"document_id":"21bac5f922f18e036b67f8ac938fccc238adc55c","doc_idx":1158}
