{"question":"What is the corporation that operates the space station ortibing Soloris?","answers":["The name of the Corporeation is DBA.","DBA"],"document_id":"2e24e035fddb9b96430c9bb2cf45d44facac6fc8","doc_idx":197}
{"question":"Who is the scientist approached by emmisaries of the corporation?","answers":[" Chris Kelvin is approached.","Dr","Dr. Chris Kelvin"],"document_id":"2e24e035fddb9b96430c9bb2cf45d44facac6fc8","doc_idx":197}
{"question":"Why is the scientist approached?","answers":["To come to the space station and investigate something that is happening.","He is given a message from his friend to come to the space station."],"document_id":"2e24e035fddb9b96430c9bb2cf45d44facac6fc8","doc_idx":197}
{"question":"What does the scientist ag ree to do?","answers":["go on a solo mission to Solaris","He agrees to do a solo mission and bring the crew home safelly."],"document_id":"2e24e035fddb9b96430c9bb2cf45d44facac6fc8","doc_idx":197}
{"question":"What does the scientilst learn when  he reaches the space station?","answers":[" and most other crew died or disappeared.","He learned that Gibarian committed suicide","His friend has committed suicide and most of the crew have died or disappeared."],"document_id":"2e24e035fddb9b96430c9bb2cf45d44facac6fc8","doc_idx":197}
{"question":"What are the names of the surviving crew  members?","answers":["Snow and Gordon are the names of t he survivors.","Snow and Dr. Gordon"],"document_id":"2e24e035fddb9b96430c9bb2cf45d44facac6fc8","doc_idx":197}
{"question":"How does the scientist try to save the replica of his wife Rheya?","answers":["He puts her in an escape pod and jettisons her into space.","He puts her in an escape pod and jettisons it into space."],"document_id":"2e24e035fddb9b96430c9bb2cf45d44facac6fc8","doc_idx":197}
{"question":"How does Gordon attempt to solve the problem of the replicas?","answers":["He develops an apparatus that will destroy the replicas.","Creates apparatus to destroy replicas."],"document_id":"2e24e035fddb9b96430c9bb2cf45d44facac6fc8","doc_idx":197}
{"question":"In the end what does the scientist decide to do?","answers":["stay on the space station","He decides to stay on Solaris."],"document_id":"2e24e035fddb9b96430c9bb2cf45d44facac6fc8","doc_idx":197}
{"question":"What does  scientist decide is his situation?","answers":["He and wife have forgiven each other.","That his perception of home away from home could merely be a convenience."],"document_id":"2e24e035fddb9b96430c9bb2cf45d44facac6fc8","doc_idx":197}
{"question":"What does Dr. Chris Kelvin do?","answers":["tries to save the replica of his wife","Clinical psychologist"],"document_id":"2e24e035fddb9b96430c9bb2cf45d44facac6fc8","doc_idx":197}
{"question":"What planet is the space station orbiting?","answers":["Solaris"],"document_id":"2e24e035fddb9b96430c9bb2cf45d44facac6fc8","doc_idx":197}
{"question":"What is the scientist's name who is friends with Dr. Kelvin?","answers":["Dr. Gibarian"],"document_id":"2e24e035fddb9b96430c9bb2cf45d44facac6fc8","doc_idx":197}
{"question":"Why was Gibarian not answering Kelvin's calls?","answers":["he committed suicide","She committed suicide"],"document_id":"2e24e035fddb9b96430c9bb2cf45d44facac6fc8","doc_idx":197}
{"question":"Who does Kelvin dream about?","answers":["Rheya","His dead wife Rheya"],"document_id":"2e24e035fddb9b96430c9bb2cf45d44facac6fc8","doc_idx":197}
{"question":"Why did Kelvin walk out on Rheya?","answers":["She terminated a pregnancy.","She terminated her pregnancy"],"document_id":"2e24e035fddb9b96430c9bb2cf45d44facac6fc8","doc_idx":197}
{"question":"How does Rheya die?","answers":["she commits suicide","Suicide"],"document_id":"2e24e035fddb9b96430c9bb2cf45d44facac6fc8","doc_idx":197}
{"question":"What happens to Rheya after she dies?","answers":["She self-resurrects","She self-resurrects."],"document_id":"2e24e035fddb9b96430c9bb2cf45d44facac6fc8","doc_idx":197}
{"question":"Why can't the ship return to earth?","answers":["The ship's fuel cell reactor was drained.","The fuel cell reactor is drained."],"document_id":"2e24e035fddb9b96430c9bb2cf45d44facac6fc8","doc_idx":197}
{"question":"What happens after Kelvin cuts his finger off?","answers":["It immediately heals","The wound immediately heals."],"document_id":"2e24e035fddb9b96430c9bb2cf45d44facac6fc8","doc_idx":197}
{"question":"How does Gibarian die?","answers":["He commits suicide.","he commits suicide"],"document_id":"2e24e035fddb9b96430c9bb2cf45d44facac6fc8","doc_idx":197}
{"question":"How many crew have survived when Kelvin arrives?","answers":["Two"],"document_id":"2e24e035fddb9b96430c9bb2cf45d44facac6fc8","doc_idx":197}
{"question":"Why did Kelvin walk out on the real Rheya?","answers":["he discovers Rheya terminated a pregnancy","She secretly terminated a pregnancy that made Kelvin walk out on her."],"document_id":"2e24e035fddb9b96430c9bb2cf45d44facac6fc8","doc_idx":197}
{"question":"What did Kelvin do to the first replica Rheya? ","answers":["Puts her in an escape pod and jetisons it into space.","leads her into an escape pod and jettisons it off into space"],"document_id":"2e24e035fddb9b96430c9bb2cf45d44facac6fc8","doc_idx":197}
{"question":"Out of the two surviving crew members which one admits to being a replica?","answers":["Snow"],"document_id":"2e24e035fddb9b96430c9bb2cf45d44facac6fc8","doc_idx":197}
{"question":"Where is Snow's body found?","answers":["Stashed in a ceiling vent.","In a ceiling vent"],"document_id":"2e24e035fddb9b96430c9bb2cf45d44facac6fc8","doc_idx":197}
{"question":"What happens to make the replicas appear?","answers":["They are dreamed about.","People dream them into existence."],"document_id":"2e24e035fddb9b96430c9bb2cf45d44facac6fc8","doc_idx":197}
{"question":"What is Kelvin chopping up when he cuts his finger?","answers":["vegetables","Vegetables."],"document_id":"2e24e035fddb9b96430c9bb2cf45d44facac6fc8","doc_idx":197}
{"question":"What is the name of the smaller space vehicle that is prepared for escape? ","answers":["Athena.","Athena"],"document_id":"2e24e035fddb9b96430c9bb2cf45d44facac6fc8","doc_idx":197}
{"question":"Whose son appears as a replica to help Kelvin?","answers":["Gibarian's.","Gibarian's"],"document_id":"2e24e035fddb9b96430c9bb2cf45d44facac6fc8","doc_idx":197}
