{"question":"Why did Paul kill Lilian?","answers":["To run off with Helen.","To run away with her sister."],"document_id":"ccde92fd5de1e67f17e10d9e0cd3375ce4efcf23","doc_idx":884}
{"question":"Where did the Liptons find Lilian's body?","answers":["In the emergency exit panel.","Emergency exit panel."],"document_id":"ccde92fd5de1e67f17e10d9e0cd3375ce4efcf23","doc_idx":884}
{"question":"What happened the day after the Liptons met Lilian?","answers":["Lillian died of a heart attack.","Lilian died."],"document_id":"ccde92fd5de1e67f17e10d9e0cd3375ce4efcf23","doc_idx":884}
{"question":"Who does Paul kidnap?","answers":["Carol.","Paul kidnaps Carol."],"document_id":"ccde92fd5de1e67f17e10d9e0cd3375ce4efcf23","doc_idx":884}
{"question":"Where did Mr. House dump Lilian's body?","answers":["Pile of scrap metal.","In a melting furnace."],"document_id":"ccde92fd5de1e67f17e10d9e0cd3375ce4efcf23","doc_idx":884}
{"question":"How much were Larry and Carol demanding from Paul?","answers":["000.","$200"],"document_id":"ccde92fd5de1e67f17e10d9e0cd3375ce4efcf23","doc_idx":884}
{"question":"What does Paul demand in exchange for Carol?","answers":["Lilian's body.","Lillians' body"],"document_id":"ccde92fd5de1e67f17e10d9e0cd3375ce4efcf23","doc_idx":884}
{"question":"Why were the Liptons shocked by Lilian's death?","answers":[" a heart attack was the last thing they were expecting.","Lilian seemed healthy.","Because Lillian seemed so healthy"],"document_id":"ccde92fd5de1e67f17e10d9e0cd3375ce4efcf23","doc_idx":884}
{"question":"How did the Liptons come across Lilian's body?","answers":["They discovered her body in the emergency exit panel.","From being trapped in a lift."],"document_id":"ccde92fd5de1e67f17e10d9e0cd3375ce4efcf23","doc_idx":884}
{"question":"Whose dead body was actually in Lilian's apartment?","answers":["Her sister's body.","Lilian's rich sister."],"document_id":"ccde92fd5de1e67f17e10d9e0cd3375ce4efcf23","doc_idx":884}
{"question":"How does Lilian die?","answers":["She was killed.","A heart attack"],"document_id":"ccde92fd5de1e67f17e10d9e0cd3375ce4efcf23","doc_idx":884}
{"question":"Why is Carol suspicious of Paul?","answers":["He's happy for someone whose wife died.","Because of his cheerfulness."],"document_id":"ccde92fd5de1e67f17e10d9e0cd3375ce4efcf23","doc_idx":884}
{"question":"Why does Lilian doubt that Lilian was buried?","answers":["Because she discovers an urn in the apartment"," contradicting the husband's story.","She finds a urn in Paul's apartment."],"document_id":"ccde92fd5de1e67f17e10d9e0cd3375ce4efcf23","doc_idx":884}
{"question":"Where does Helen hide when Paul nearly catches her in his apartment?","answers":["Under his bed.","Under the bed"],"document_id":"ccde92fd5de1e67f17e10d9e0cd3375ce4efcf23","doc_idx":884}
{"question":"Where did Carol see a Lilian lookalike?","answers":["On a bus","A bus"],"document_id":"ccde92fd5de1e67f17e10d9e0cd3375ce4efcf23","doc_idx":884}
{"question":"How much money do Larry and Carol demand of Paul?","answers":["200","000 dollars","$200","000"],"document_id":"ccde92fd5de1e67f17e10d9e0cd3375ce4efcf23","doc_idx":884}
{"question":"What is being played during the chase in the theater?","answers":["The Lady from Shanghai","The Lady from Shanghai by Orson Welles"],"document_id":"ccde92fd5de1e67f17e10d9e0cd3375ce4efcf23","doc_idx":884}
{"question":"Who turned out to be Lilian's lookalike?","answers":["Her sister","Her rich sister"],"document_id":"ccde92fd5de1e67f17e10d9e0cd3375ce4efcf23","doc_idx":884}
{"question":"Why did Paul doublecross Lilian?","answers":["He wanted to be with a young actress named Helen.","So he could run off with Helen."],"document_id":"ccde92fd5de1e67f17e10d9e0cd3375ce4efcf23","doc_idx":884}
{"question":"Where did Larry and Carol meet their neighbors?","answers":["In the elevator","They met in an elevetor."],"document_id":"ccde92fd5de1e67f17e10d9e0cd3375ce4efcf23","doc_idx":884}
{"question":"How did Lilian die?","answers":["she didnt","Lilian died of a heart attack."],"document_id":"ccde92fd5de1e67f17e10d9e0cd3375ce4efcf23","doc_idx":884}
{"question":"Why were Larry and Carol surprised by her death?","answers":["Lilian did not look or act unhealthy at all.","Larry did not seem upset by her death."],"document_id":"ccde92fd5de1e67f17e10d9e0cd3375ce4efcf23","doc_idx":884}
{"question":"What made carol feel funny about Pauls reaction to his wife's death?","answers":["He was in a good mood","She felt that he was too happy afterwards."],"document_id":"ccde92fd5de1e67f17e10d9e0cd3375ce4efcf23","doc_idx":884}
{"question":"What does Carol do about how she feels?","answers":["She decides to do research on Paul and goes to see him.","she starts investigating"],"document_id":"ccde92fd5de1e67f17e10d9e0cd3375ce4efcf23","doc_idx":884}
{"question":"What does Carol find in the apartment?","answers":["She finds plans to travel for paul and another woman.","She finds an urn in the apartment."],"document_id":"ccde92fd5de1e67f17e10d9e0cd3375ce4efcf23","doc_idx":884}
{"question":"Who does Carol contact to tell of what she's found?","answers":["the police","She tells a good male friend of hers."],"document_id":"ccde92fd5de1e67f17e10d9e0cd3375ce4efcf23","doc_idx":884}
{"question":"What did Carol, Ted, and Larry overhear Paul and Helen discussing?","answers":["money","They were going over financial plans."],"document_id":"ccde92fd5de1e67f17e10d9e0cd3375ce4efcf23","doc_idx":884}
{"question":"Why were the police called?","answers":["Helen shoots Paul","A dead body was found."],"document_id":"ccde92fd5de1e67f17e10d9e0cd3375ce4efcf23","doc_idx":884}
