{"question":"What medical condition did Whale continue to suffer from?","answers":["Strokes","repeated strokes"],"document_id":"3753ff3da0842f8a1609e3cee8bb506c3b5b63f2","doc_idx":1190}
{"question":"What job was Boone hired to do for Whale?","answers":["Gardener","To be his gardener."],"document_id":"3753ff3da0842f8a1609e3cee8bb506c3b5b63f2","doc_idx":1190}
{"question":"Who are the two \"monsters\" mentioned in the story?","answers":["Boris Karloff and Elsa Lanchester"],"document_id":"3753ff3da0842f8a1609e3cee8bb506c3b5b63f2","doc_idx":1190}
{"question":"What is Boone's son's name?","answers":["Michael","Michael."],"document_id":"3753ff3da0842f8a1609e3cee8bb506c3b5b63f2","doc_idx":1190}
{"question":"Who hosted the party, mentioned in the story, for Princess Margaret?","answers":["George Cukor"],"document_id":"3753ff3da0842f8a1609e3cee8bb506c3b5b63f2","doc_idx":1190}
{"question":"What happens at Princess Margaret's party that is an excuse for Whale and Boone to leave?","answers":["A sudden rainstorm.","A rain storm"],"document_id":"3753ff3da0842f8a1609e3cee8bb506c3b5b63f2","doc_idx":1190}
{"question":"Who is Whale's longtime housemaid?","answers":["Hanna.","Hanna"],"document_id":"3753ff3da0842f8a1609e3cee8bb506c3b5b63f2","doc_idx":1190}
{"question":"What pieces of work did Whale famously direct?","answers":["The Bride of Frankenstein.","Frankenstein and Bride of Frankenstein"],"document_id":"3753ff3da0842f8a1609e3cee8bb506c3b5b63f2","doc_idx":1190}
{"question":"What did Boone do to help Whale?","answers":["Pose for his drawings","gardener"],"document_id":"3753ff3da0842f8a1609e3cee8bb506c3b5b63f2","doc_idx":1190}
{"question":"After Whale and Boone's disagreement where did Hanna find Whale?","answers":["Dead in the pool","Dead in his pool."],"document_id":"3753ff3da0842f8a1609e3cee8bb506c3b5b63f2","doc_idx":1190}
{"question":"What is James Whale's claim to fame? ","answers":["He directed Frankenstein and Bride of Frankenstein.","He was the director of the films Frankenstein and Bride of Frankenstein"],"document_id":"3753ff3da0842f8a1609e3cee8bb506c3b5b63f2","doc_idx":1190}
{"question":"Who is Clayton Boone to James at the beginning of the story? ","answers":["His gardener.","He is his gardener."],"document_id":"3753ff3da0842f8a1609e3cee8bb506c3b5b63f2","doc_idx":1190}
{"question":"How did James Whale sign his drawing of Frankenstein that he gave to Clayton? ","answers":["With \"To Clayton. Friend?\"","To Clayton. Friend?"],"document_id":"3753ff3da0842f8a1609e3cee8bb506c3b5b63f2","doc_idx":1190}
{"question":"What did Clayton's friends think were James' intentions with Clayton? ","answers":["He just wanted to get him into bed.","sexual"],"document_id":"3753ff3da0842f8a1609e3cee8bb506c3b5b63f2","doc_idx":1190}
{"question":"What did Clayton do when James detailed his past sexual exploits?","answers":["He stormed out.","He stormed out and then later made him agree to never speak of his homosexuality to him again."],"document_id":"3753ff3da0842f8a1609e3cee8bb506c3b5b63f2","doc_idx":1190}
{"question":"Why was Clayton uncomfortable with his friendship with James? ","answers":["Because he was a known homosexual.","James was gay and Clayton was straight; unsure as to what James' intentions with their friendship may be should he want it to become more."],"document_id":"3753ff3da0842f8a1609e3cee8bb506c3b5b63f2","doc_idx":1190}
{"question":"What causes James' depression at the beginning of the story? ","answers":["He misses his fame and glory days and he's getting older."," attractiveness and health are all slipping away.","Realizing that his life"],"document_id":"3753ff3da0842f8a1609e3cee8bb506c3b5b63f2","doc_idx":1190}
{"question":"How did James feel after he and Boone attended the party for Princess Margaret? ","answers":["More depressed.","James felt depressed."],"document_id":"3753ff3da0842f8a1609e3cee8bb506c3b5b63f2","doc_idx":1190}
{"question":"How did Boone react when James' finally made a sexual advance? ","answers":["He was very angry and physically attacked him.","He got angry and attacked James."],"document_id":"3753ff3da0842f8a1609e3cee8bb506c3b5b63f2","doc_idx":1190}
{"question":"Why did James ask Clayton to kill him? ","answers":["To put him out of his misery.","to end his torment"],"document_id":"3753ff3da0842f8a1609e3cee8bb506c3b5b63f2","doc_idx":1190}
{"question":"Who does Whale live with?","answers":["Hanna","His housekeeper Hanna."],"document_id":"3753ff3da0842f8a1609e3cee8bb506c3b5b63f2","doc_idx":1190}
{"question":"What war was Whale in?","answers":["World War I","World War One."],"document_id":"3753ff3da0842f8a1609e3cee8bb506c3b5b63f2","doc_idx":1190}
{"question":"Who poses for Whale's sketches?","answers":["Clayton Boone."," Clayton Boone.","His Gardener"],"document_id":"3753ff3da0842f8a1609e3cee8bb506c3b5b63f2","doc_idx":1190}
{"question":"Who hosts the party Boone and Whale go to?","answers":["George Cukor","George Cukor."],"document_id":"3753ff3da0842f8a1609e3cee8bb506c3b5b63f2","doc_idx":1190}
{"question":"What does Boone wear when his clothes get wet?","answers":["A towel wrapped around his waist.","A towel."],"document_id":"3753ff3da0842f8a1609e3cee8bb506c3b5b63f2","doc_idx":1190}
{"question":"Where does Whale kiss Boone?","answers":["His shoulder.","On his shoulder."],"document_id":"3753ff3da0842f8a1609e3cee8bb506c3b5b63f2","doc_idx":1190}
{"question":"Who does Whale ask to kill him?","answers":["Clayton Boone."],"document_id":"3753ff3da0842f8a1609e3cee8bb506c3b5b63f2","doc_idx":1190}
{"question":"What do Boone and his son watch on TV?","answers":["The Bride of Frankenstein."],"document_id":"3753ff3da0842f8a1609e3cee8bb506c3b5b63f2","doc_idx":1190}
{"question":"How does Boone prove to his son that he was friends with Whale?","answers":["he shows him a signed picture with the word \"Friend?\"","He shows him a sketch of the monster."],"document_id":"3753ff3da0842f8a1609e3cee8bb506c3b5b63f2","doc_idx":1190}
