{"question":"Who is Dragon?","answers":["A cat.","the farmer's cat"],"document_id":"04954299c7b6bdc7b31b951bc0daa277353576a9","doc_idx":1109}
{"question":"Who Killed Mr. Frisby?","answers":[" the cat","Dragon"],"document_id":"04954299c7b6bdc7b31b951bc0daa277353576a9","doc_idx":1109}
{"question":"Why do the rats agree to help Ms. Frisby?","answers":["out of respect for her husband for helping them escape NIMH","Her husband made their escape from the lab possible."],"document_id":"04954299c7b6bdc7b31b951bc0daa277353576a9","doc_idx":1109}
{"question":"Why did Ms. Frisby volunteer to drug Dragon?","answers":["The other rats were too large to fit into the hole in the wall.","because she was small enough to fit through the hole to get to Dragon's bowl"],"document_id":"04954299c7b6bdc7b31b951bc0daa277353576a9","doc_idx":1109}
{"question":"Who put Ms. Frisby in a cage?","answers":["Billy.","Billy"],"document_id":"04954299c7b6bdc7b31b951bc0daa277353576a9","doc_idx":1109}
{"question":"Who saves Ms. Frisby from the cage?","answers":["Justin"],"document_id":"04954299c7b6bdc7b31b951bc0daa277353576a9","doc_idx":1109}
{"question":"Why does Ms. Frisby need their house moved?","answers":["Because the farmer Mr. Fitzgibbons is about to plow the field.","So her son Timothy can recover from illness and to avoid the plow."],"document_id":"04954299c7b6bdc7b31b951bc0daa277353576a9","doc_idx":1109}
{"question":"Why do 10 rats stay behind when the other evacuate?","answers":["To make it appear they have not abandoned the hole.","To make it look as though the rat hole wasn't abandoned"],"document_id":"04954299c7b6bdc7b31b951bc0daa277353576a9","doc_idx":1109}
{"question":"How many rats escape the gases?","answers":["8"],"document_id":"04954299c7b6bdc7b31b951bc0daa277353576a9","doc_idx":1109}
{"question":"How did the rats know they were going to be exterminated?","answers":["Ms. Frisby overheard a conversation while in the cage.","Mrs. Frisby overhead the Fitzgibbons talking about it."],"document_id":"04954299c7b6bdc7b31b951bc0daa277353576a9","doc_idx":1109}
{"question":"What happened to Timothy's father?","answers":["Dragon killed him.","he was killed by the farmer's cat"],"document_id":"04954299c7b6bdc7b31b951bc0daa277353576a9","doc_idx":1109}
{"question":"Who helped the rats escape from NIMH?","answers":["Mr. Frisby and Mr. Ages","Mrs. Frisby"],"document_id":"04954299c7b6bdc7b31b951bc0daa277353576a9","doc_idx":1109}
{"question":"When does the owl agree to help Timothy get moved?","answers":["After he confirms that Mrs. Frisbey is Jonathan's widow.","when he learns Mrs. Frisby is Jonathan's window"],"document_id":"04954299c7b6bdc7b31b951bc0daa277353576a9","doc_idx":1109}
{"question":"How did Nicodemus learn to read?","answers":["the humans at NIMH performed experiments on him which increased his intelligence","Because of drugs given to the rats."],"document_id":"04954299c7b6bdc7b31b951bc0daa277353576a9","doc_idx":1109}
{"question":"Why are some rats interested in establishing a new farming colony?","answers":["To end their dependence upon humans","they don't want to be dependent on humans any longer"],"document_id":"04954299c7b6bdc7b31b951bc0daa277353576a9","doc_idx":1109}
{"question":"When did Billy catch Mrs. Frisby?","answers":["When she sneaks into the house to drug Dragon the cat","when she tried to drug the cat"],"document_id":"04954299c7b6bdc7b31b951bc0daa277353576a9","doc_idx":1109}
{"question":"When did people become interested in the rat colony on Mr. Fitzgibbons' farm?","answers":["After a group of rats electrocuted themselves at a hardware store trying to steal parts for a small motor.","After the rats were electrocuted at the hardware store"],"document_id":"04954299c7b6bdc7b31b951bc0daa277353576a9","doc_idx":1109}
{"question":"Who rescued Timothy's mother from the cage?","answers":["Justin"],"document_id":"04954299c7b6bdc7b31b951bc0daa277353576a9","doc_idx":1109}
{"question":"How did the rats fool the exterminators?","answers":["They filled the holes with rubbish to look like normal rats.","by destroying their underground rooms and filling some with garbage"," in order to appear like regular rats"],"document_id":"04954299c7b6bdc7b31b951bc0daa277353576a9","doc_idx":1109}
{"question":"Where was the farm cat's bowl?","answers":["Inside the house.","inside the house"],"document_id":"04954299c7b6bdc7b31b951bc0daa277353576a9","doc_idx":1109}
{"question":"Who is the head of the field mice?","answers":["Mrs. Frisby is the head of the field mice.","Mrs. Frisby"],"document_id":"04954299c7b6bdc7b31b951bc0daa277353576a9","doc_idx":1109}
{"question":"What ailment does Timothy have?","answers":["Pneumonia","He has pneumonia."],"document_id":"04954299c7b6bdc7b31b951bc0daa277353576a9","doc_idx":1109}
{"question":"Who is the farmer on the property?","answers":["Mr. Fitzgibbon","Mr. Fitzgibbon."],"document_id":"04954299c7b6bdc7b31b951bc0daa277353576a9","doc_idx":1109}
{"question":"Who gives Mrs. Frisby medication for Timothy?","answers":["Mr. Ages.","Mr. Ages"],"document_id":"04954299c7b6bdc7b31b951bc0daa277353576a9","doc_idx":1109}
{"question":"Whose life does Mrs. Frisby save from the Cat?","answers":["Jeremy"," a young crow."],"document_id":"04954299c7b6bdc7b31b951bc0daa277353576a9","doc_idx":1109}
{"question":"Who is the leader of the rats?","answers":["Nicodemus"],"document_id":"04954299c7b6bdc7b31b951bc0daa277353576a9","doc_idx":1109}
{"question":"What rat left the colony because they disagreed with \"The Plan\"?","answers":["Jenner"],"document_id":"04954299c7b6bdc7b31b951bc0daa277353576a9","doc_idx":1109}
{"question":"Who catches Mrs. Frisby?","answers":["Billy.","Billy"],"document_id":"04954299c7b6bdc7b31b951bc0daa277353576a9","doc_idx":1109}
{"question":"Where does Billy put Mrs. Frisby?","answers":["In a cage","in a cage"],"document_id":"04954299c7b6bdc7b31b951bc0daa277353576a9","doc_idx":1109}
{"question":"Out of the 10 rats in the hole, how many escape?","answers":["Eight","8 rats escape"],"document_id":"04954299c7b6bdc7b31b951bc0daa277353576a9","doc_idx":1109}
