{"question":"What did the sign in the store read?","answers":["Jews Welcome.","Jews Welcome"],"document_id":"1718768b5be4356b36704d5876db8009916ecd0c","doc_idx":1140}
{"question":"Which group did Mohammed Ali Paula Abdul Rahim lead?","answers":["Kwanzaa Liberation Front.","The Kwanzaa Liberation Front."],"document_id":"1718768b5be4356b36704d5876db8009916ecd0c","doc_idx":1140}
{"question":"Who was the son of Santa?","answers":["Santa son was Damian.","Damian."],"document_id":"1718768b5be4356b36704d5876db8009916ecd0c","doc_idx":1140}
{"question":"Which holidays did Damian want to destroy?","answers":["Kwanzaa and Hanukkah.","Hanukkah and Kwanzaa"],"document_id":"1718768b5be4356b36704d5876db8009916ecd0c","doc_idx":1140}
{"question":"How many years was there peace between religions?","answers":["At least three decades.","A few decades."],"document_id":"1718768b5be4356b36704d5876db8009916ecd0c","doc_idx":1140}
{"question":"Where did the final battle occur?","answers":["Israeli atomic clock","The Israeli atomic clock."],"document_id":"1718768b5be4356b36704d5876db8009916ecd0c","doc_idx":1140}
{"question":"Who did Damian murder?","answers":["his father","His father."],"document_id":"1718768b5be4356b36704d5876db8009916ecd0c","doc_idx":1140}
{"question":"Who did Mordechai fall in love with?","answers":["Esther Bloomenbergensteinenthal","Ester Bloomenbergensteinenthal."],"document_id":"1718768b5be4356b36704d5876db8009916ecd0c","doc_idx":1140}
{"question":"Who stepped on Mordechai's toy?","answers":["Santa.","Santa Claus"],"document_id":"1718768b5be4356b36704d5876db8009916ecd0c","doc_idx":1140}
{"question":"How did Mordechai cheer himself up?","answers":["By spinning his dreidal.","Spins his dreidel."],"document_id":"1718768b5be4356b36704d5876db8009916ecd0c","doc_idx":1140}
{"question":"What is the religion of the main character Mordechai?","answers":["Judaism","He was a Jew."],"document_id":"1718768b5be4356b36704d5876db8009916ecd0c","doc_idx":1140}
{"question":"What does Santa Claus do to Mordechai's toy?","answers":["He steps on it.","crushes it"],"document_id":"1718768b5be4356b36704d5876db8009916ecd0c","doc_idx":1140}
{"question":"What is Mordechai's grown-up nickname?","answers":["Hebrew Hammer.","The Hebrew Hammer"],"document_id":"1718768b5be4356b36704d5876db8009916ecd0c","doc_idx":1140}
{"question":"What two holidays does Damian despise?","answers":["Hanukkah and Kwanzaa.","Hanukkah and Kwanzaa"],"document_id":"1718768b5be4356b36704d5876db8009916ecd0c","doc_idx":1140}
{"question":"What group celebrates Kwanzaa?","answers":["African American.","African-Americans"],"document_id":"1718768b5be4356b36704d5876db8009916ecd0c","doc_idx":1140}
{"question":"What group celebrates Hanukkah?","answers":["Jews.","The Jewish people"],"document_id":"1718768b5be4356b36704d5876db8009916ecd0c","doc_idx":1140}
{"question":"What Jewish toy is Mordechai playing with that is crushed?","answers":["Dreidel.","Dreidel"],"document_id":"1718768b5be4356b36704d5876db8009916ecd0c","doc_idx":1140}
{"question":"Where does the final battle take place between Mordechai and Damian?","answers":["at the Israeli atomic clock","The Israeli Atomic Clock"],"document_id":"1718768b5be4356b36704d5876db8009916ecd0c","doc_idx":1140}
{"question":"What action did Mordechai perform to cheer himself up?","answers":["spinning his dreidel","He spins his dreidel."],"document_id":"1718768b5be4356b36704d5876db8009916ecd0c","doc_idx":1140}
{"question":"Why was Christmas a hard time for Mordechai?","answers":["He was teased for celebrating Hanukkah instead","because Christians excluded him and tormented him for celebrating being Jewish"],"document_id":"1718768b5be4356b36704d5876db8009916ecd0c","doc_idx":1140}
{"question":"What holiday did Mordechai celebrate instead of Christmas?","answers":["Hanukkah"],"document_id":"1718768b5be4356b36704d5876db8009916ecd0c","doc_idx":1140}
{"question":"When Mordechai grew up, what was his nicname?","answers":["the Hebrew Hammer","The Hebrew Hammer"],"document_id":"1718768b5be4356b36704d5876db8009916ecd0c","doc_idx":1140}
{"question":"Who was Esther Bloomenbergensteinenthal?","answers":["Mordechai's love interest.","Mordecai's love interest and daughter of the leader of the Jewish Justice League"],"document_id":"1718768b5be4356b36704d5876db8009916ecd0c","doc_idx":1140}
{"question":"Who was Esther Bloomenbergensteinenthal's father?","answers":["Mohammed Ali Paula Abdul Rahim","Chief of the Jewish Justice Leauge"],"document_id":"1718768b5be4356b36704d5876db8009916ecd0c","doc_idx":1140}
{"question":"What kind of a demeanor did Mordechai have as an adult?","answers":["tough-guy","a tough-guy demeanor"],"document_id":"1718768b5be4356b36704d5876db8009916ecd0c","doc_idx":1140}
{"question":"How did the Jewish community look at him?","answers":["as a local hero","as a hero"],"document_id":"1718768b5be4356b36704d5876db8009916ecd0c","doc_idx":1140}
{"question":"Why was the first Santa rude to Mordechai?","answers":["Because he was Jewish","because Mordechai was a Jew"],"document_id":"1718768b5be4356b36704d5876db8009916ecd0c","doc_idx":1140}
{"question":"What did the first Santa do to Mordechai?","answers":["Stomped on his dreidel.","crushed his toy and gave him the finger"],"document_id":"1718768b5be4356b36704d5876db8009916ecd0c","doc_idx":1140}
