{"question":"How did Jordan Belfort breach his cooperation deal with the FBI?","answers":["He wore a wire to work.","Jordan slipped a warning note to Donnie."],"document_id":"ee3ba75510af0a8836993c57cb6809b676edad63","doc_idx":1026}
{"question":"What did Jordan Belfort immediately do after finding out that Aunt Emma died?","answers":["travel to Switzerland","He attempted to sail to to Switzerland."],"document_id":"ee3ba75510af0a8836993c57cb6809b676edad63","doc_idx":1026}
{"question":"What is the name of the FBI agent who is investigating Jordan Belfort? ","answers":["Patrick Denham"],"document_id":"ee3ba75510af0a8836993c57cb6809b676edad63","doc_idx":1026}
{"question":"What caused Jordan Belfort's job to be terminated at L.F. Rothschild?","answers":["Black Monday","Black Friday"],"document_id":"ee3ba75510af0a8836993c57cb6809b676edad63","doc_idx":1026}
{"question":"Why did Teresa Belfort divorce her husband?","answers":["she found out Jordan had an affair with Naomi.","He was having an affair."],"document_id":"ee3ba75510af0a8836993c57cb6809b676edad63","doc_idx":1026}
{"question":"What caused the plane crash that was flying Jordan Belfort to Geneva?","answers":["A bird flew into the engine.","a seagull flies into the engine"],"document_id":"ee3ba75510af0a8836993c57cb6809b676edad63","doc_idx":1026}
{"question":"How did Jordan Belfort make a living after his release from prison?","answers":["hosting seminars","He hosted seminars on sales techniques."],"document_id":"ee3ba75510af0a8836993c57cb6809b676edad63","doc_idx":1026}
{"question":"Who was in the car with Jordan Belfort when he crashed?","answers":["Skylar"," Skylar Belfort.","His daughter"],"document_id":"ee3ba75510af0a8836993c57cb6809b676edad63","doc_idx":1026}
{"question":"What did Jordan Belfort illegally do upon securing the IPO of Steven Madden?","answers":["He made $22 million in 3 hours.","He made $22 million."],"document_id":"ee3ba75510af0a8836993c57cb6809b676edad63","doc_idx":1026}
{"question":"Where did Jordan Belfort hid his illegal money?","answers":["Swiss bank","In a Swiss bank account."],"document_id":"ee3ba75510af0a8836993c57cb6809b676edad63","doc_idx":1026}
{"question":"How did Jordan breach his cooperation deal with the FBI?","answers":["He wore a wire to work.","He gave Donnie a note to warn him about the wire."],"document_id":"ee3ba75510af0a8836993c57cb6809b676edad63","doc_idx":1026}
{"question":"How did aunt Emma die?","answers":["Heart attack","She had a heart attack."],"document_id":"ee3ba75510af0a8836993c57cb6809b676edad63","doc_idx":1026}
{"question":"Why did Jordan force his yacht captain to sail to Monaco?","answers":["to avoid border control","To avoid border patrols."],"document_id":"ee3ba75510af0a8836993c57cb6809b676edad63","doc_idx":1026}
{"question":"What did Jordan use to illegally make $22 million dollars?","answers":["The IPO of Steve Madden.","Steve Madden's IPO"],"document_id":"ee3ba75510af0a8836993c57cb6809b676edad63","doc_idx":1026}
{"question":"How does Jordan make a living after being released from prison?","answers":["hosting sales technique seminars","He hosts seminars on sales technique."],"document_id":"ee3ba75510af0a8836993c57cb6809b676edad63","doc_idx":1026}
{"question":"Where were Jordan, Donnie and their wives going when they learned about aunt Emma's death?","answers":["Italy","They were taking a yacht trip to Italy."],"document_id":"ee3ba75510af0a8836993c57cb6809b676edad63","doc_idx":1026}
{"question":"How was aunt Emma able to stay out of the reach of the American authorities?","answers":["She was a British national.","She is a British national."],"document_id":"ee3ba75510af0a8836993c57cb6809b676edad63","doc_idx":1026}
{"question":"What happens to the yacht when Jordan forced the captain to sail to Monaco?","answers":["capsizes","It is capsized in a storm."],"document_id":"ee3ba75510af0a8836993c57cb6809b676edad63","doc_idx":1026}
{"question":"What had happened that led to Jordan and Teresa getting a divorce?","answers":["Jordan had an affair","Jordan had an affair with Naomi."],"document_id":"ee3ba75510af0a8836993c57cb6809b676edad63","doc_idx":1026}
{"question":"How did Jordan know that his phones were being wiretapped?","answers":["from his PI","His private investigator him."],"document_id":"ee3ba75510af0a8836993c57cb6809b676edad63","doc_idx":1026}
{"question":"What job did Jordan Belfort secure on Wall Street? ","answers":["Stockbroker","Stockbroker."],"document_id":"ee3ba75510af0a8836993c57cb6809b676edad63","doc_idx":1026}
{"question":"What does Mark Hanna teach Belfort about his job as a stockbroker?","answers":["that his only job is to make money for himself","that hisonly  job is to make money for himself"],"document_id":"ee3ba75510af0a8836993c57cb6809b676edad63","doc_idx":1026}
{"question":"Who is Donnie Azoff?","answers":["Jordan's neighbor","The neighbor Jordan befriends and co-founds their company with"],"document_id":"ee3ba75510af0a8836993c57cb6809b676edad63","doc_idx":1026}
{"question":"What is the name of Jordan gives his new firm?","answers":["Stratton Oakmont","Stratton Oakmont."],"document_id":"ee3ba75510af0a8836993c57cb6809b676edad63","doc_idx":1026}
{"question":"Who leads the FBI to Jordan's arrest?","answers":["Saurel"],"document_id":"ee3ba75510af0a8836993c57cb6809b676edad63","doc_idx":1026}
{"question":"Why does Jordan wear a wire to work?","answers":["deal with the FBI","he is trying to get information on his colleagues in order for leniency in court"],"document_id":"ee3ba75510af0a8836993c57cb6809b676edad63","doc_idx":1026}
{"question":"Who does Jordan inform about his wearing a wire in the office?","answers":["Donnie.","Donnie"],"document_id":"ee3ba75510af0a8836993c57cb6809b676edad63","doc_idx":1026}
{"question":"What happens to the FBI's deal with Jordan?","answers":["It is thrown out because they discovered he is in breaching the deal with the note he passed to Donnie","Jordan breaches deal by telling Donnie about the wire"],"document_id":"ee3ba75510af0a8836993c57cb6809b676edad63","doc_idx":1026}
{"question":"What does Jordan's sentence entail?","answers":["3 years in a minimum security prison.","Three years in a minimum security prison"],"document_id":"ee3ba75510af0a8836993c57cb6809b676edad63","doc_idx":1026}
{"question":"What does Jordan do for a living after his sentence is up?","answers":["hosting seminars on sales techniques","he is hosting seminars on sales technique"],"document_id":"ee3ba75510af0a8836993c57cb6809b676edad63","doc_idx":1026}
